{
  "active_availability_lag_months": 4,
  "active_availability_method": "fixed_regulatory_lag",
  "active_workstream": "stage126_m1_financial_baseline",
  "baseline_branch": "origin/main",
  "baseline_commit": "5f56be5b2e49e66c54b451994a5e36c4fcc754d9",
  "broad_codal_capture_stopped": true,
  "contract_version": "stage126_m1_primary_development_tuning_v1",
  "current_batch": null,
  "current_stage": "Stage126",
  "development_modeling_authorized": true,
  "final_test_access_authorized": false,
  "final_test_evaluation_performed": false,
  "final_test_predictor_values_inspected": false,
  "final_test_target_values_inspected": false,
  "final_test_unlocked": false,
  "financial_data_researcher_verified_frozen": true,
  "four_month_regulatory_lag_locked": true,
  "gate_b_started": true,
  "generated_at_utc": "2026-07-22T10:47:33Z",
  "generated_from_commit": "9a5e25c2390c1b5c82f8917bd0a47f10c1ca544f",
  "historical_six_month_decision_retained": true,
  "last_completed_micro_part": "stage125-part5-readiness-closure",
  "last_stage_commit": "9a5e25c2390c1b5c82f8917bd0a47f10c1ca544f",
  "m1_primary_development_tuning_completed": true,
  "m1_robustness_completed": false,
  "m1_robustness_started": false,
  "m2_data_collected": false,
  "m3_data_collected": false,
  "m4_data_collected": false,
  "modeling_authorized": true,
  "modeling_started": true,
  "next_research_action_id": "stage126-m1-financial-baseline",
  "observed_branch": "stage126-m1-primary-development-tuning",
  "observed_repository_head_commit": "9a5e25c2390c1b5c82f8917bd0a47f10c1ca544f",
  "part3b_completed": false,
  "part3c_leakage_safe_finalization_completed": true,
  "part4_statistical_analysis_plan_locked": true,
  "qc_all_pass": true,
  "qc_assertions": 65,
  "qc_failed": 0,
  "qc_source_commit": "28c4e464808a74a6d459f8236ba432cf4a66b1d5",
  "repository": "abtinasg/papermali",
  "row_level_publish_datetime_collection_required": false,
  "schema_version": 2,
  "selected_qc_path": "project/stage126/stage126_m1_primary_development_tuning_qc_report.json",
  "selected_qc_scope": "stage126_m1_financial_baseline",
  "six_month_lag_superseded": true,
  "stage125_completed": true,
  "stage126_authorized": true,
  "stage126_m1_entry_ready": true,
  "stage126_started": true,
  "state_fingerprint": "bc5bdcf8f1a3ae3256c679aa7d2922b2eadfc1d8e1992e6a6525a4644aa93a98",
  "tickers": [
    "اردستان",
    "اروند",
    "اپال",
    "بالبر",
    "بترانس",
    "برکت",
    "بموتو",
    "بوعلی",
    "بکاب",
    "بکام",
    "تاپیکو",
    "تپمپی",
    "تکمبا",
    "ثشرق",
    "ثنوسا",
    "جم",
    "جم پیلن",
    "حپترو",
    "حکشتی",
    "خاذین",
    "خبهمن",
    "ختوقا",
    "خرینگ",
    "خمحور",
    "خمهر",
    "خنصیر",
    "خوساز",
    "خچرخش",
    "خکمک",
    "ددام",
    "درازک",
    "دروز",
    "دسبحا",
    "دسینا",
    "دشیمی",
    "دیران",
    "ذوب",
    "رانفور",
    "رمپنا",
    "زمگسا",
    "زپارس",
    "سآبیک",
    "ساراب",
    "ساربیل",
    "ساروم",
    "سبجنو",
    "سبهان",
    "ستران",
    "سخاش",
    "سخزر",
    "سخوز",
    "سدشت",
    "سدور",
    "سرود",
    "سشرق",
    "سصفها",
    "سغرب",
    "سفارس",
    "سقاین",
    "سمازن",
    "سنیر",
    "سهگمت",
    "سپاها",
    "سپید",
    "سکرد",
    "سیلام",
    "شاراک",
    "شبریز",
    "شبندر",
    "شدوص",
    "شغدیر",
    "شفارس",
    "شلعاب",
    "شپارس",
    "شپنا",
    "شکربن",
    "شکلر",
    "شیران",
    "غبهنوش",
    "غدام",
    "غسالم",
    "غشان",
    "غشهد",
    "غنوش",
    "غگل",
    "فاذر",
    "فارس",
    "فایرا",
    "فباهنر",
    "فجام",
    "فجر",
    "فخوز",
    "فرآور",
    "فسرب",
    "فسپا",
    "فمراد",
    "فملی",
    "فنورد",
    "فولاژ",
    "فپنتا",
    "لابسا",
    "لبوتان",
    "لخزر",
    "لسرما",
    "نوری",
    "های وب",
    "همراه",
    "ومعادن",
    "وملی",
    "وکغدیر",
    "پارس",
    "پارسان",
    "پدرخش",
    "پرداخت",
    "پسهند",
    "پلاسک",
    "پی‌پاد",
    "چافست",
    "چکارن",
    "کاوه",
    "کبافق",
    "کرازی",
    "کروی",
    "کفرا",
    "کفپارس",
    "کهمدا",
    "کویر",
    "کگاز",
    "کگل",
    "کیمیاتک"
  ],
  "verified_master_created": true
}
